{
  "bookId": 9,
  "book": "1 Samuel",
  "chapter": 28,
  "version": "BSB",
  "verses": {
    "1": [
      {
        "surface": "days",
        "lemma": "yom"
      },
      {
        "surface": "the Philistines",
        "lemma": "pelishti"
      },
      {
        "surface": "gathered",
        "lemma": "qavats"
      },
      {
        "surface": "their forces",
        "lemma": "machaneh"
      },
      {
        "surface": "for warfare",
        "lemma": "tsava"
      },
      {
        "surface": "against Israel",
        "lemma": "yisrael"
      },
      {
        "surface": "So Achish",
        "lemma": "akhish"
      },
      {
        "surface": "David",
        "lemma": "david"
      },
      {
        "surface": "You must understand",
        "lemma": "yada"
      },
      {
        "surface": "and your men",
        "lemma": "enosh"
      },
      {
        "surface": "to battle",
        "lemma": "machaneh"
      }
    ],
    "2": [
      {
        "surface": "David",
        "lemma": "david"
      },
      {
        "surface": "Then",
        "lemma": "ken"
      },
      {
        "surface": "will come to know",
        "lemma": "yada"
      },
      {
        "surface": "your servant",
        "lemma": "eved"
      },
      {
        "surface": "Very well",
        "lemma": "ken"
      },
      {
        "surface": "Achish",
        "lemma": "akhish"
      },
      {
        "surface": "I will make you",
        "lemma": "sum"
      },
      {
        "surface": "my bodyguard",
        "lemma": "shamar"
      },
      {
        "surface": "for life",
        "lemma": "yom"
      }
    ],
    "3": [
      {
        "surface": "Now by this time Samuel",
        "lemma": "shemuel"
      },
      {
        "surface": "had died",
        "lemma": "mut"
      },
      {
        "surface": "Israel",
        "lemma": "yisrael"
      },
      {
        "surface": "had mourned",
        "lemma": "saphad"
      },
      {
        "surface": "and buried him",
        "lemma": "qavar"
      },
      {
        "surface": "in Ramah",
        "lemma": "ramah"
      },
      {
        "surface": "his own city",
        "lemma": "ir"
      },
      {
        "surface": "And Saul",
        "lemma": "shaul"
      },
      {
        "surface": "had removed",
        "lemma": "sur"
      },
      {
        "surface": "the mediums",
        "lemma": "ov"
      },
      {
        "surface": "and spiritists",
        "lemma": "yiddoni"
      },
      {
        "surface": "from the land",
        "lemma": "erets"
      }
    ],
    "4": [
      {
        "surface": "The Philistines",
        "lemma": "pelishti"
      },
      {
        "surface": "gathered together",
        "lemma": "qavats"
      },
      {
        "surface": "and camped",
        "lemma": "chanah"
      },
      {
        "surface": "at Shunem",
        "lemma": "shunem"
      },
      {
        "surface": "while Saul",
        "lemma": "shaul"
      },
      {
        "surface": "gathered",
        "lemma": "qavats"
      },
      {
        "surface": "Israel",
        "lemma": "yisrael"
      },
      {
        "surface": "and camped",
        "lemma": "chanah"
      },
      {
        "surface": "at Gilboa",
        "lemma": "gilboa"
      }
    ],
    "5": [
      {
        "surface": "When Saul",
        "lemma": "shaul"
      },
      {
        "surface": "the Philistine",
        "lemma": "pelishti"
      },
      {
        "surface": "army",
        "lemma": "machaneh"
      },
      {
        "surface": "he",
        "lemma": "lev"
      },
      {
        "surface": "was afraid",
        "lemma": "yare"
      },
      {
        "surface": "and trembled",
        "lemma": "charad"
      },
      {
        "surface": "violently",
        "lemma": "meod"
      }
    ],
    "6": [
      {
        "surface": "He inquired",
        "lemma": "shaal"
      },
      {
        "surface": "of the LORD",
        "lemma": "yehovah"
      },
      {
        "surface": "but the LORD",
        "lemma": "yehovah"
      },
      {
        "surface": "answer him",
        "lemma": "un"
      },
      {
        "surface": "by dreams",
        "lemma": "chalom"
      },
      {
        "surface": "Urim",
        "lemma": "urim"
      },
      {
        "surface": "prophets",
        "lemma": "navi"
      }
    ],
    "7": [
      {
        "surface": "Then Saul",
        "lemma": "shaul"
      },
      {
        "surface": "to his servants",
        "lemma": "eved"
      },
      {
        "surface": "Find",
        "lemma": "baqash"
      },
      {
        "surface": "a woman",
        "lemma": "ishshah"
      },
      {
        "surface": "who is",
        "lemma": "baalah"
      },
      {
        "surface": "a medium",
        "lemma": "ov"
      },
      {
        "surface": "so I can go",
        "lemma": "halakh"
      },
      {
        "surface": "and consult",
        "lemma": "darash"
      },
      {
        "surface": "There is",
        "lemma": "hinneh"
      },
      {
        "surface": "vvv",
        "lemma": "ishshah"
      },
      {
        "surface": "vvv",
        "lemma": "baalah"
      },
      {
        "surface": "a medium",
        "lemma": "ov"
      },
      {
        "surface": "vvv",
        "lemma": "endor"
      },
      {
        "surface": "at Endor",
        "lemma": "endor"
      },
      {
        "surface": "his servants",
        "lemma": "eved"
      }
    ],
    "8": [
      {
        "surface": "So Saul",
        "lemma": "shaul"
      },
      {
        "surface": "disguised himself",
        "lemma": "chaphas"
      },
      {
        "surface": "by putting on",
        "lemma": "lavash"
      },
      {
        "surface": "different",
        "lemma": "acher"
      },
      {
        "surface": "clothes",
        "lemma": "beged"
      },
      {
        "surface": "and he set out",
        "lemma": "halakh"
      },
      {
        "surface": "two",
        "lemma": "shenayim"
      },
      {
        "surface": "of his men",
        "lemma": "enosh"
      },
      {
        "surface": "the woman",
        "lemma": "ishshah"
      },
      {
        "surface": "at night",
        "lemma": "laylah"
      },
      {
        "surface": "Consult",
        "lemma": "qasam"
      },
      {
        "surface": "a spirit",
        "lemma": "ov"
      },
      {
        "surface": "Bring up",
        "lemma": "alah"
      }
    ],
    "9": [
      {
        "surface": "But the woman",
        "lemma": "ishshah"
      },
      {
        "surface": "Surely",
        "lemma": "hinneh"
      },
      {
        "surface": "know",
        "lemma": "yada"
      },
      {
        "surface": "Saul",
        "lemma": "shaul"
      },
      {
        "surface": "he has killed",
        "lemma": "karat"
      },
      {
        "surface": "the mediums",
        "lemma": "ov"
      },
      {
        "surface": "and spiritists",
        "lemma": "yiddoni"
      },
      {
        "surface": "the land",
        "lemma": "erets"
      },
      {
        "surface": "Why",
        "lemma": "mah"
      },
      {
        "surface": "set a trap",
        "lemma": "naqash"
      },
      {
        "surface": "vvv",
        "lemma": "nephesh"
      },
      {
        "surface": "to get me killed",
        "lemma": "mut"
      }
    ],
    "10": [
      {
        "surface": "Then Saul",
        "lemma": "shaul"
      },
      {
        "surface": "swore",
        "lemma": "shava"
      },
      {
        "surface": "by the LORD",
        "lemma": "yehovah"
      },
      {
        "surface": "As surely as the LORD",
        "lemma": "yehovah"
      },
      {
        "surface": "lives",
        "lemma": "chay"
      },
      {
        "surface": "punishment",
        "lemma": "avan"
      },
      {
        "surface": "shall come upon you",
        "lemma": "qarah"
      },
      {
        "surface": "for",
        "lemma": "davar"
      }
    ],
    "11": [
      {
        "surface": "Whom",
        "lemma": "mi"
      },
      {
        "surface": "shall I bring up",
        "lemma": "alah"
      },
      {
        "surface": "the woman",
        "lemma": "ishshah"
      },
      {
        "surface": "Bring up",
        "lemma": "alah"
      },
      {
        "surface": "Samuel",
        "lemma": "shemuel"
      }
    ],
    "12": [
      {
        "surface": "But when the woman",
        "lemma": "ishshah"
      },
      {
        "surface": "Samuel",
        "lemma": "shemuel"
      },
      {
        "surface": "she cried out",
        "lemma": "zaaq"
      },
      {
        "surface": "in a loud",
        "lemma": "gadol"
      },
      {
        "surface": "voice",
        "lemma": "qol"
      },
      {
        "surface": "and",
        "lemma": "ishshah"
      },
      {
        "surface": "to Saul",
        "lemma": "shaul"
      },
      {
        "surface": "Why",
        "lemma": "mah"
      },
      {
        "surface": "have you deceived me",
        "lemma": "ramah"
      },
      {
        "surface": "are Saul",
        "lemma": "shaul"
      }
    ],
    "13": [
      {
        "surface": "be afraid",
        "lemma": "yare"
      },
      {
        "surface": "the king",
        "lemma": "melekh"
      },
      {
        "surface": "What",
        "lemma": "mah"
      },
      {
        "surface": "a god",
        "lemma": "elohim"
      },
      {
        "surface": "coming up",
        "lemma": "alah"
      },
      {
        "surface": "the earth",
        "lemma": "erets"
      },
      {
        "surface": "the woman",
        "lemma": "ishshah"
      }
    ],
    "14": [
      {
        "surface": "What",
        "lemma": "mah"
      },
      {
        "surface": "does he look like",
        "lemma": "toar"
      },
      {
        "surface": "An old",
        "lemma": "zaqen"
      },
      {
        "surface": "man",
        "lemma": "ish"
      },
      {
        "surface": "is coming up",
        "lemma": "alah"
      },
      {
        "surface": "wearing",
        "lemma": "atah"
      },
      {
        "surface": "a robe",
        "lemma": "meil"
      },
      {
        "surface": "So Saul",
        "lemma": "shaul"
      },
      {
        "surface": "knew",
        "lemma": "yada"
      },
      {
        "surface": "was Samuel",
        "lemma": "shemuel"
      },
      {
        "surface": "and he bowed",
        "lemma": "qadad"
      },
      {
        "surface": "facedown",
        "lemma": "aph"
      },
      {
        "surface": "in reverence",
        "lemma": "shachah"
      }
    ],
    "15": [
      {
        "surface": "Then Samuel",
        "lemma": "shemuel"
      },
      {
        "surface": "Saul",
        "lemma": "shaul"
      },
      {
        "surface": "Why",
        "lemma": "mah"
      },
      {
        "surface": "have you disturbed me",
        "lemma": "ragaz"
      },
      {
        "surface": "by bringing me up",
        "lemma": "alah"
      },
      {
        "surface": "deeply",
        "lemma": "meod"
      },
      {
        "surface": "distressed",
        "lemma": "tsarar"
      },
      {
        "surface": "Saul",
        "lemma": "shaul"
      },
      {
        "surface": "The Philistines",
        "lemma": "pelishti"
      },
      {
        "surface": "are fighting",
        "lemma": "lacham"
      },
      {
        "surface": "and God",
        "lemma": "elohim"
      },
      {
        "surface": "has turned away",
        "lemma": "sur"
      },
      {
        "surface": "longer",
        "lemma": "od"
      },
      {
        "surface": "answers me",
        "lemma": "un"
      },
      {
        "surface": "by",
        "lemma": "yad"
      },
      {
        "surface": "prophets",
        "lemma": "navi"
      },
      {
        "surface": "by dreams",
        "lemma": "chalom"
      },
      {
        "surface": "to tell me",
        "lemma": "yada"
      },
      {
        "surface": "what",
        "lemma": "mah"
      }
    ],
    "16": [
      {
        "surface": "Why",
        "lemma": "mah"
      },
      {
        "surface": "do you consult me",
        "lemma": "shaal"
      },
      {
        "surface": "Samuel",
        "lemma": "shemuel"
      },
      {
        "surface": "since the LORD",
        "lemma": "yehovah"
      },
      {
        "surface": "has turned away",
        "lemma": "sur"
      },
      {
        "surface": "your enemy",
        "lemma": "ar"
      }
    ],
    "17": [
      {
        "surface": "He",
        "lemma": "yehovah"
      },
      {
        "surface": "He spoke",
        "lemma": "davar"
      },
      {
        "surface": "through me",
        "lemma": "yad"
      },
      {
        "surface": "The LORD",
        "lemma": "yehovah"
      },
      {
        "surface": "the kingdom",
        "lemma": "mamlakhah"
      },
      {
        "surface": "out of your hand",
        "lemma": "yad"
      },
      {
        "surface": "to your neighbor",
        "lemma": "rea"
      },
      {
        "surface": "David",
        "lemma": "david"
      }
    ],
    "18": [
      {
        "surface": "the LORD",
        "lemma": "yehovah"
      },
      {
        "surface": "His burning",
        "lemma": "charon"
      },
      {
        "surface": "anger",
        "lemma": "aph"
      },
      {
        "surface": "against Amalek",
        "lemma": "amaleq"
      },
      {
        "surface": "the LORD",
        "lemma": "yehovah"
      },
      {
        "surface": "today",
        "lemma": "yom"
      }
    ],
    "19": [
      {
        "surface": "the LORD",
        "lemma": "yehovah"
      },
      {
        "surface": "Israel",
        "lemma": "yisrael"
      },
      {
        "surface": "into the hand",
        "lemma": "yad"
      },
      {
        "surface": "of the Philistines",
        "lemma": "pelishti"
      },
      {
        "surface": "and tomorrow",
        "lemma": "machar"
      },
      {
        "surface": "and your sons",
        "lemma": "ben"
      },
      {
        "surface": "the LORD",
        "lemma": "yehovah"
      },
      {
        "surface": "the army",
        "lemma": "machaneh"
      },
      {
        "surface": "of Israel",
        "lemma": "yisrael"
      },
      {
        "surface": "into the hand",
        "lemma": "yad"
      },
      {
        "surface": "of the Philistines",
        "lemma": "pelishti"
      }
    ],
    "20": [
      {
        "surface": "Immediately",
        "lemma": "mahar"
      },
      {
        "surface": "Saul",
        "lemma": "shaul"
      },
      {
        "surface": "fell",
        "lemma": "naphal"
      },
      {
        "surface": "flat",
        "lemma": "melo"
      },
      {
        "surface": "on the ground",
        "lemma": "erets"
      },
      {
        "surface": "terrified",
        "lemma": "yare"
      },
      {
        "surface": "by the words",
        "lemma": "davar"
      },
      {
        "surface": "of Samuel",
        "lemma": "shemuel"
      },
      {
        "surface": "his strength",
        "lemma": "koach"
      },
      {
        "surface": "eaten",
        "lemma": "akhal"
      },
      {
        "surface": "anything",
        "lemma": "lechem"
      },
      {
        "surface": "day",
        "lemma": "yom"
      },
      {
        "surface": "night",
        "lemma": "laylah"
      }
    ],
    "21": [
      {
        "surface": "When the woman",
        "lemma": "ishshah"
      },
      {
        "surface": "Saul",
        "lemma": "shaul"
      },
      {
        "surface": "distraught he was",
        "lemma": "bahal"
      },
      {
        "surface": "Look",
        "lemma": "hinneh"
      },
      {
        "surface": "your maidservant",
        "lemma": "shiphchah"
      },
      {
        "surface": "your voice",
        "lemma": "qol"
      },
      {
        "surface": "I took",
        "lemma": "sum"
      },
      {
        "surface": "my life",
        "lemma": "nephesh"
      },
      {
        "surface": "in my hands",
        "lemma": "kaph"
      },
      {
        "surface": "you told",
        "lemma": "davar"
      }
    ],
    "22": [
      {
        "surface": "Now",
        "lemma": "attah"
      },
      {
        "surface": "please",
        "lemma": "na"
      },
      {
        "surface": "to your servant",
        "lemma": "shiphchah"
      },
      {
        "surface": "and let me set",
        "lemma": "sum"
      },
      {
        "surface": "a morsel",
        "lemma": "pat"
      },
      {
        "surface": "of bread",
        "lemma": "lechem"
      },
      {
        "surface": "before you",
        "lemma": "paneh"
      },
      {
        "surface": "so you may eat",
        "lemma": "akhal"
      },
      {
        "surface": "the strength",
        "lemma": "koach"
      },
      {
        "surface": "go",
        "lemma": "halakh"
      },
      {
        "surface": "on your way",
        "lemma": "derekh"
      }
    ],
    "23": [
      {
        "surface": "Saul refused",
        "lemma": "maen"
      },
      {
        "surface": "eat",
        "lemma": "akhal"
      },
      {
        "surface": "But his servants",
        "lemma": "eved"
      },
      {
        "surface": "the woman",
        "lemma": "ishshah"
      },
      {
        "surface": "in urging",
        "lemma": "parats"
      },
      {
        "surface": "their voice",
        "lemma": "qol"
      },
      {
        "surface": "He got up",
        "lemma": "qamay"
      },
      {
        "surface": "from the ground",
        "lemma": "erets"
      },
      {
        "surface": "the bed",
        "lemma": "mittah"
      }
    ],
    "24": [
      {
        "surface": "The woman",
        "lemma": "ishshah"
      },
      {
        "surface": "had a fattened",
        "lemma": "marbeq"
      },
      {
        "surface": "calf",
        "lemma": "egel"
      },
      {
        "surface": "at her house",
        "lemma": "bet"
      },
      {
        "surface": "and she quickly",
        "lemma": "mahar"
      },
      {
        "surface": "slaughtered it",
        "lemma": "zavach"
      },
      {
        "surface": "She also took",
        "lemma": "laqach"
      },
      {
        "surface": "flour",
        "lemma": "qemach"
      },
      {
        "surface": "kneaded it",
        "lemma": "lush"
      },
      {
        "surface": "and baked",
        "lemma": "aphah"
      },
      {
        "surface": "unleavened bread",
        "lemma": "matstsah"
      }
    ],
    "25": [
      {
        "surface": "She served",
        "lemma": "nagash"
      },
      {
        "surface": "it to",
        "lemma": "paneh"
      },
      {
        "surface": "Saul",
        "lemma": "shaul"
      },
      {
        "surface": "and his servants",
        "lemma": "eved"
      },
      {
        "surface": "and they ate",
        "lemma": "akhal"
      },
      {
        "surface": "night",
        "lemma": "laylah"
      },
      {
        "surface": "they got up",
        "lemma": "qamay"
      },
      {
        "surface": "and left",
        "lemma": "halakh"
      }
    ]
  },
  "themeLemmas": [
    "shaul",
    "shemuel",
    "mah"
  ]
}