{
  "bookId": 14,
  "book": "2 Chronicles",
  "chapter": 10,
  "version": "BSB",
  "verses": {
    "1": [
      {
        "surface": "Then Rehoboam",
        "lemma": "rechavam"
      },
      {
        "surface": "went",
        "lemma": "halakh"
      },
      {
        "surface": "to Shechem",
        "lemma": "shekhem"
      },
      {
        "surface": "Israel",
        "lemma": "yisrael"
      },
      {
        "surface": "there",
        "lemma": "shekhem"
      },
      {
        "surface": "to make him king",
        "lemma": "malakh"
      }
    ],
    "2": [
      {
        "surface": "When Jeroboam",
        "lemma": "yarovam"
      },
      {
        "surface": "son",
        "lemma": "ben"
      },
      {
        "surface": "of Nebat",
        "lemma": "nevat"
      },
      {
        "surface": "he",
        "lemma": "yarovam"
      },
      {
        "surface": "from Egypt",
        "lemma": "mitsrayim"
      },
      {
        "surface": "he had fled",
        "lemma": "barach"
      },
      {
        "surface": "from King",
        "lemma": "melekh"
      },
      {
        "surface": "Solomon",
        "lemma": "shelomoh"
      }
    ],
    "3": [
      {
        "surface": "So they sent for",
        "lemma": "shalach"
      },
      {
        "surface": "and he",
        "lemma": "yarovam"
      },
      {
        "surface": "Israel",
        "lemma": "yisrael"
      },
      {
        "surface": "Rehoboam",
        "lemma": "rechavam"
      },
      {
        "surface": "and said",
        "lemma": "davar"
      }
    ],
    "4": [
      {
        "surface": "put a heavy",
        "lemma": "qashah"
      },
      {
        "surface": "yoke",
        "lemma": "ol"
      },
      {
        "surface": "But now",
        "lemma": "attah"
      },
      {
        "surface": "you must lighten",
        "lemma": "qalal"
      },
      {
        "surface": "the burden",
        "lemma": "qasheh"
      },
      {
        "surface": "service",
        "lemma": "avodah"
      },
      {
        "surface": "and the heavy",
        "lemma": "kaved"
      },
      {
        "surface": "yoke",
        "lemma": "ol"
      },
      {
        "surface": "and we will serve you",
        "lemma": "avad"
      }
    ],
    "5": [
      {
        "surface": "in",
        "lemma": "od"
      },
      {
        "surface": "three",
        "lemma": "shalosh"
      },
      {
        "surface": "days",
        "lemma": "yom"
      },
      {
        "surface": "So the people",
        "lemma": "am"
      },
      {
        "surface": "departed",
        "lemma": "halakh"
      }
    ],
    "6": [
      {
        "surface": "Then King",
        "lemma": "melekh"
      },
      {
        "surface": "Rehoboam",
        "lemma": "rechavam"
      },
      {
        "surface": "consulted",
        "lemma": "yaats"
      },
      {
        "surface": "the elders",
        "lemma": "zaqen"
      },
      {
        "surface": "had served",
        "lemma": "amad"
      },
      {
        "surface": "Solomon",
        "lemma": "shelomoh"
      },
      {
        "surface": "his lifetime",
        "lemma": "chay"
      },
      {
        "surface": "How",
        "lemma": "ekh"
      },
      {
        "surface": "advise me",
        "lemma": "yaats"
      },
      {
        "surface": "people",
        "lemma": "am"
      }
    ],
    "7": [
      {
        "surface": "They replied",
        "lemma": "davar"
      },
      {
        "surface": "kind",
        "lemma": "tov"
      },
      {
        "surface": "people",
        "lemma": "am"
      },
      {
        "surface": "and please them",
        "lemma": "ratsah"
      },
      {
        "surface": "by speaking",
        "lemma": "davar"
      },
      {
        "surface": "kind",
        "lemma": "tov"
      },
      {
        "surface": "words",
        "lemma": "davar"
      },
      {
        "surface": "servants",
        "lemma": "eved"
      }
    ],
    "8": [
      {
        "surface": "But Rehoboam rejected",
        "lemma": "azav"
      },
      {
        "surface": "the advice",
        "lemma": "etsah"
      },
      {
        "surface": "of the elders",
        "lemma": "zaqen"
      },
      {
        "surface": "instead, he consulted",
        "lemma": "yaats"
      },
      {
        "surface": "the young men",
        "lemma": "yeled"
      },
      {
        "surface": "had grown up",
        "lemma": "gadal"
      },
      {
        "surface": "and served",
        "lemma": "amad"
      },
      {
        "surface": "him",
        "lemma": "paneh"
      }
    ],
    "9": [
      {
        "surface": "What",
        "lemma": "mah"
      },
      {
        "surface": "message",
        "lemma": "davar"
      },
      {
        "surface": "advise",
        "lemma": "yaats"
      },
      {
        "surface": "people",
        "lemma": "am"
      },
      {
        "surface": "have spoken",
        "lemma": "davar"
      },
      {
        "surface": "Lighten",
        "lemma": "qalal"
      },
      {
        "surface": "the yoke",
        "lemma": "ol"
      }
    ],
    "10": [
      {
        "surface": "The young men",
        "lemma": "yeled"
      },
      {
        "surface": "had grown up",
        "lemma": "gadal"
      },
      {
        "surface": "replied",
        "lemma": "davar"
      },
      {
        "surface": "This is how",
        "lemma": "koh"
      },
      {
        "surface": "these people",
        "lemma": "am"
      },
      {
        "surface": "said",
        "lemma": "davar"
      },
      {
        "surface": "made our yoke",
        "lemma": "ol"
      },
      {
        "surface": "heavy",
        "lemma": "kavad"
      },
      {
        "surface": "must make it lighter",
        "lemma": "qalal"
      },
      {
        "surface": "This is what",
        "lemma": "koh"
      },
      {
        "surface": "My little finger",
        "lemma": "qoten"
      },
      {
        "surface": "is thicker",
        "lemma": "avah"
      },
      {
        "surface": "waist",
        "lemma": "moten"
      }
    ],
    "11": [
      {
        "surface": "Whereas",
        "lemma": "attah"
      },
      {
        "surface": "burdened",
        "lemma": "amas"
      },
      {
        "surface": "you with a heavy",
        "lemma": "kaved"
      },
      {
        "surface": "yoke",
        "lemma": "ol"
      },
      {
        "surface": "will add",
        "lemma": "yasaph"
      },
      {
        "surface": "your yoke",
        "lemma": "ol"
      },
      {
        "surface": "scourged",
        "lemma": "yasar"
      },
      {
        "surface": "with whips",
        "lemma": "shot"
      },
      {
        "surface": "with scorpions",
        "lemma": "aqrav"
      }
    ],
    "12": [
      {
        "surface": "After three",
        "lemma": "shelishi"
      },
      {
        "surface": "days",
        "lemma": "yom"
      },
      {
        "surface": "Jeroboam",
        "lemma": "yarovam"
      },
      {
        "surface": "the people",
        "lemma": "am"
      },
      {
        "surface": "Rehoboam",
        "lemma": "rechavam"
      },
      {
        "surface": "the king",
        "lemma": "melekh"
      },
      {
        "surface": "on the third",
        "lemma": "shelishi"
      },
      {
        "surface": "day",
        "lemma": "yom"
      }
    ],
    "13": [
      {
        "surface": "And the king",
        "lemma": "melekh"
      },
      {
        "surface": "answered them",
        "lemma": "un"
      },
      {
        "surface": "harshly",
        "lemma": "qasheh"
      },
      {
        "surface": "King",
        "lemma": "melekh"
      },
      {
        "surface": "Rehoboam",
        "lemma": "rechavam"
      },
      {
        "surface": "rejected",
        "lemma": "azav"
      },
      {
        "surface": "the advice",
        "lemma": "etsah"
      },
      {
        "surface": "of the elders",
        "lemma": "zaqen"
      }
    ],
    "14": [
      {
        "surface": "and spoke",
        "lemma": "davar"
      },
      {
        "surface": "as the young men",
        "lemma": "yeled"
      },
      {
        "surface": "had advised",
        "lemma": "etsah"
      },
      {
        "surface": "Whereas my father made your yoke",
        "lemma": "ol"
      },
      {
        "surface": "heavy",
        "lemma": "kavad"
      },
      {
        "surface": "will add",
        "lemma": "yasaph"
      },
      {
        "surface": "scourged",
        "lemma": "yasar"
      },
      {
        "surface": "with whips",
        "lemma": "shot"
      },
      {
        "surface": "with scorpions",
        "lemma": "aqrav"
      }
    ],
    "15": [
      {
        "surface": "So the king",
        "lemma": "melekh"
      },
      {
        "surface": "the people",
        "lemma": "am"
      },
      {
        "surface": "this turn of events",
        "lemma": "nesibbah"
      },
      {
        "surface": "God",
        "lemma": "elohim"
      },
      {
        "surface": "the LORD",
        "lemma": "yehovah"
      },
      {
        "surface": "might fulfill",
        "lemma": "qamay"
      },
      {
        "surface": "the word",
        "lemma": "davar"
      },
      {
        "surface": "He had spoken",
        "lemma": "davar"
      },
      {
        "surface": "through",
        "lemma": "yad"
      },
      {
        "surface": "Ahijah",
        "lemma": "achiyyah"
      },
      {
        "surface": "the Shilonite",
        "lemma": "shiloni"
      },
      {
        "surface": "Jeroboam",
        "lemma": "yarovam"
      },
      {
        "surface": "son",
        "lemma": "ben"
      },
      {
        "surface": "of Nebat",
        "lemma": "nevat"
      }
    ],
    "16": [
      {
        "surface": "Israel saw",
        "lemma": "yisrael"
      },
      {
        "surface": "the king",
        "lemma": "melekh"
      },
      {
        "surface": "to them",
        "lemma": "am"
      },
      {
        "surface": "the king",
        "lemma": "melekh"
      },
      {
        "surface": "What",
        "lemma": "mah"
      },
      {
        "surface": "portion",
        "lemma": "cheleq"
      },
      {
        "surface": "in David",
        "lemma": "david"
      },
      {
        "surface": "inheritance",
        "lemma": "nachalah"
      },
      {
        "surface": "in the son",
        "lemma": "ben"
      },
      {
        "surface": "of Jesse",
        "lemma": "yishay"
      },
      {
        "surface": "To your tents",
        "lemma": "hoel"
      },
      {
        "surface": "O Israel",
        "lemma": "yisrael"
      },
      {
        "surface": "now",
        "lemma": "bet"
      },
      {
        "surface": "to your own house",
        "lemma": "attah"
      },
      {
        "surface": "O David",
        "lemma": "david"
      },
      {
        "surface": "the Israelites",
        "lemma": "yisrael"
      },
      {
        "surface": "went",
        "lemma": "halakh"
      },
      {
        "surface": "home",
        "lemma": "hoel"
      }
    ],
    "17": [
      {
        "surface": "but Rehoboam",
        "lemma": "rechavam"
      },
      {
        "surface": "still reigned",
        "lemma": "malakh"
      },
      {
        "surface": "the Israelites",
        "lemma": "ben"
      },
      {
        "surface": "in the cities",
        "lemma": "ir"
      },
      {
        "surface": "of Judah",
        "lemma": "yehudah"
      }
    ],
    "18": [
      {
        "surface": "Then King",
        "lemma": "melekh"
      },
      {
        "surface": "Rehoboam",
        "lemma": "rechavam"
      },
      {
        "surface": "sent out",
        "lemma": "shalach"
      },
      {
        "surface": "Hadoram",
        "lemma": "hadoram"
      },
      {
        "surface": "of the forced labor",
        "lemma": "mas"
      },
      {
        "surface": "but the Israelites",
        "lemma": "ben"
      },
      {
        "surface": "stoned",
        "lemma": "ragam"
      },
      {
        "surface": "to death",
        "lemma": "mut"
      },
      {
        "surface": "And King",
        "lemma": "melekh"
      },
      {
        "surface": "Rehoboam",
        "lemma": "rechavam"
      },
      {
        "surface": "mounted",
        "lemma": "alah"
      },
      {
        "surface": "his chariot",
        "lemma": "merkavah"
      },
      {
        "surface": "in haste",
        "lemma": "amats"
      },
      {
        "surface": "and escaped",
        "lemma": "nus"
      },
      {
        "surface": "to Jerusalem",
        "lemma": "yerushalaim"
      }
    ],
    "19": [
      {
        "surface": "this",
        "lemma": "yom"
      },
      {
        "surface": "Israel",
        "lemma": "yisrael"
      },
      {
        "surface": "has been in rebellion",
        "lemma": "pasah"
      },
      {
        "surface": "against the house",
        "lemma": "bet"
      },
      {
        "surface": "of David",
        "lemma": "david"
      }
    ]
  },
  "themeLemmas": [
    "rechavam",
    "ol",
    "yisrael"
  ]
}