{
  "bookId": 3,
  "book": "Leviticus",
  "chapter": 7,
  "version": "BSB",
  "verses": {
    "1": [
      {
        "surface": "is the law",
        "lemma": "torah"
      },
      {
        "surface": "of the guilt offering",
        "lemma": "asham"
      },
      {
        "surface": "most",
        "lemma": "qodesh"
      },
      {
        "surface": "holy",
        "lemma": "qodesh"
      }
    ],
    "2": [
      {
        "surface": "The guilt offering",
        "lemma": "asham"
      },
      {
        "surface": "must be slaughtered",
        "lemma": "shachat"
      },
      {
        "surface": "in the place",
        "lemma": "maqom"
      },
      {
        "surface": "the burnt offering",
        "lemma": "olah"
      },
      {
        "surface": "is slaughtered",
        "lemma": "shachat"
      },
      {
        "surface": "and the priest shall splatter",
        "lemma": "zaraq"
      },
      {
        "surface": "its blood",
        "lemma": "dam"
      },
      {
        "surface": "on all sides",
        "lemma": "saviv"
      },
      {
        "surface": "the altar",
        "lemma": "mizbeach"
      }
    ],
    "3": [
      {
        "surface": "the fat",
        "lemma": "chelev"
      },
      {
        "surface": "shall be offered",
        "lemma": "qarav"
      },
      {
        "surface": "the fat tail",
        "lemma": "alyah"
      },
      {
        "surface": "the fat",
        "lemma": "chelev"
      },
      {
        "surface": "that covers",
        "lemma": "kasah"
      },
      {
        "surface": "the entrails",
        "lemma": "qerev"
      }
    ],
    "4": [
      {
        "surface": "both",
        "lemma": "shenayim"
      },
      {
        "surface": "kidneys",
        "lemma": "kilyah"
      },
      {
        "surface": "with the fat",
        "lemma": "chelev"
      },
      {
        "surface": "the loins",
        "lemma": "kesel"
      },
      {
        "surface": "and the lobe",
        "lemma": "yoteret"
      },
      {
        "surface": "the liver",
        "lemma": "kaved"
      },
      {
        "surface": "which is to be removed",
        "lemma": "sur"
      },
      {
        "surface": "the kidneys",
        "lemma": "kilyah"
      }
    ],
    "5": [
      {
        "surface": "The priest",
        "lemma": "kohen"
      },
      {
        "surface": "shall burn",
        "lemma": "qatar"
      },
      {
        "surface": "on the altar",
        "lemma": "mizbeach"
      },
      {
        "surface": "as a food offering",
        "lemma": "ishshah"
      },
      {
        "surface": "to the LORD",
        "lemma": "yehovah"
      },
      {
        "surface": "is a guilt offering",
        "lemma": "asham"
      }
    ],
    "6": [
      {
        "surface": "male",
        "lemma": "zakhar"
      },
      {
        "surface": "among the priests",
        "lemma": "kohen"
      },
      {
        "surface": "may eat of it",
        "lemma": "akhal"
      },
      {
        "surface": "It must be eaten",
        "lemma": "akhal"
      },
      {
        "surface": "in a holy",
        "lemma": "qadosh"
      },
      {
        "surface": "place",
        "lemma": "maqom"
      },
      {
        "surface": "most",
        "lemma": "qodesh"
      },
      {
        "surface": "holy",
        "lemma": "qodesh"
      }
    ],
    "7": [
      {
        "surface": "The guilt offering",
        "lemma": "asham"
      },
      {
        "surface": "is like the sin offering",
        "lemma": "chattaah"
      },
      {
        "surface": "the same",
        "lemma": "echad"
      },
      {
        "surface": "law",
        "lemma": "torah"
      },
      {
        "surface": "the priest",
        "lemma": "kohen"
      },
      {
        "surface": "makes atonement",
        "lemma": "kipher"
      }
    ],
    "8": [
      {
        "surface": "As for the priest",
        "lemma": "kohen"
      },
      {
        "surface": "who presents",
        "lemma": "qarav"
      },
      {
        "surface": "a burnt offering",
        "lemma": "olah"
      },
      {
        "surface": "for anyone",
        "lemma": "ish"
      },
      {
        "surface": "the hide",
        "lemma": "or"
      },
      {
        "surface": "of that offering",
        "lemma": "olah"
      }
    ],
    "9": [
      {
        "surface": "grain offering",
        "lemma": "minchah"
      },
      {
        "surface": "is baked",
        "lemma": "aphah"
      },
      {
        "surface": "in an oven",
        "lemma": "tannur"
      },
      {
        "surface": "in a pan",
        "lemma": "marcheshet"
      },
      {
        "surface": "a griddle",
        "lemma": "machavat"
      },
      {
        "surface": "the priest",
        "lemma": "kohen"
      },
      {
        "surface": "who presents",
        "lemma": "qarav"
      }
    ],
    "10": [
      {
        "surface": "grain offering",
        "lemma": "minchah"
      },
      {
        "surface": "whether dry",
        "lemma": "charev"
      },
      {
        "surface": "or mixed",
        "lemma": "balal"
      },
      {
        "surface": "with oil",
        "lemma": "shemen"
      },
      {
        "surface": "belongs equally",
        "lemma": "ish"
      },
      {
        "surface": "the sons",
        "lemma": "ben"
      },
      {
        "surface": "of Aaron",
        "lemma": "haaron"
      }
    ],
    "11": [
      {
        "surface": "is the law",
        "lemma": "torah"
      },
      {
        "surface": "vvv",
        "lemma": "zevach"
      },
      {
        "surface": "of the peace offering",
        "lemma": "shelem"
      },
      {
        "surface": "one may present",
        "lemma": "qarav"
      },
      {
        "surface": "to the LORD",
        "lemma": "yehovah"
      }
    ],
    "12": [
      {
        "surface": "he offers it",
        "lemma": "qarav"
      },
      {
        "surface": "thanksgiving",
        "lemma": "todah"
      },
      {
        "surface": "the sacrifice",
        "lemma": "zevach"
      },
      {
        "surface": "of thanksgiving",
        "lemma": "todah"
      },
      {
        "surface": "he shall offer",
        "lemma": "qarav"
      },
      {
        "surface": "unleavened",
        "lemma": "matstsah"
      },
      {
        "surface": "cakes",
        "lemma": "challah"
      },
      {
        "surface": "mixed",
        "lemma": "balal"
      },
      {
        "surface": "with olive oil",
        "lemma": "shemen"
      },
      {
        "surface": "unleavened",
        "lemma": "matstsah"
      },
      {
        "surface": "wafers",
        "lemma": "raqiq"
      },
      {
        "surface": "coated",
        "lemma": "mashach"
      },
      {
        "surface": "with oil",
        "lemma": "shemen"
      },
      {
        "surface": "and well-kneaded",
        "lemma": "ravakh"
      },
      {
        "surface": "cakes",
        "lemma": "challah"
      },
      {
        "surface": "of fine flour",
        "lemma": "solet"
      },
      {
        "surface": "mixed",
        "lemma": "balal"
      },
      {
        "surface": "with oil",
        "lemma": "shemen"
      }
    ],
    "13": [
      {
        "surface": "vvv",
        "lemma": "zevach"
      },
      {
        "surface": "his peace offering",
        "lemma": "shelem"
      },
      {
        "surface": "of thanksgiving",
        "lemma": "todah"
      },
      {
        "surface": "he is to present",
        "lemma": "qarav"
      },
      {
        "surface": "an offering",
        "lemma": "qorban"
      },
      {
        "surface": "with cakes",
        "lemma": "challah"
      },
      {
        "surface": "of leavened",
        "lemma": "chamets"
      },
      {
        "surface": "bread",
        "lemma": "lechem"
      }
    ],
    "14": [
      {
        "surface": "the cakes he must present",
        "lemma": "qarav"
      },
      {
        "surface": "one",
        "lemma": "echad"
      },
      {
        "surface": "offering",
        "lemma": "qorban"
      },
      {
        "surface": "as a contribution",
        "lemma": "terumah"
      },
      {
        "surface": "to the LORD",
        "lemma": "yehovah"
      },
      {
        "surface": "the priest",
        "lemma": "kohen"
      },
      {
        "surface": "who sprinkles",
        "lemma": "zaraq"
      },
      {
        "surface": "the blood",
        "lemma": "dam"
      },
      {
        "surface": "of the peace offering",
        "lemma": "shelem"
      }
    ],
    "15": [
      {
        "surface": "The meat",
        "lemma": "basar"
      },
      {
        "surface": "of the sacrifice",
        "lemma": "zevach"
      },
      {
        "surface": "of his peace offering",
        "lemma": "shelem"
      },
      {
        "surface": "of thanksgiving",
        "lemma": "todah"
      },
      {
        "surface": "must be eaten",
        "lemma": "akhal"
      },
      {
        "surface": "on the day",
        "lemma": "yom"
      },
      {
        "surface": "he offers it",
        "lemma": "qorban"
      },
      {
        "surface": "may be left",
        "lemma": "nuach"
      },
      {
        "surface": "morning",
        "lemma": "boqer"
      }
    ],
    "16": [
      {
        "surface": "the sacrifice",
        "lemma": "zevach"
      },
      {
        "surface": "he offers",
        "lemma": "qorban"
      },
      {
        "surface": "is a vow",
        "lemma": "neder"
      },
      {
        "surface": "a freewill offering",
        "lemma": "nedavah"
      },
      {
        "surface": "it shall be eaten",
        "lemma": "akhal"
      },
      {
        "surface": "on the day",
        "lemma": "yom"
      },
      {
        "surface": "he presents",
        "lemma": "qarav"
      },
      {
        "surface": "his sacrifice",
        "lemma": "zevach"
      },
      {
        "surface": "but the remainder",
        "lemma": "yatar"
      },
      {
        "surface": "may be eaten",
        "lemma": "akhal"
      },
      {
        "surface": "the next day",
        "lemma": "mochorat"
      }
    ],
    "17": [
      {
        "surface": "But any meat",
        "lemma": "basar"
      },
      {
        "surface": "of the sacrifice",
        "lemma": "zevach"
      },
      {
        "surface": "remaining",
        "lemma": "yatar"
      },
      {
        "surface": "until the third",
        "lemma": "shelishi"
      },
      {
        "surface": "day",
        "lemma": "yom"
      },
      {
        "surface": "vvv",
        "lemma": "esh"
      },
      {
        "surface": "must be burned up",
        "lemma": "saraph"
      }
    ],
    "18": [
      {
        "surface": "any of",
        "lemma": "akhal"
      },
      {
        "surface": "the meat",
        "lemma": "basar"
      },
      {
        "surface": "vvv",
        "lemma": "zevach"
      },
      {
        "surface": "from his peace offering",
        "lemma": "shelem"
      },
      {
        "surface": "is eaten",
        "lemma": "akhal"
      },
      {
        "surface": "on the third",
        "lemma": "shelishi"
      },
      {
        "surface": "day",
        "lemma": "yom"
      },
      {
        "surface": "be accepted",
        "lemma": "ratsah"
      },
      {
        "surface": "be credited",
        "lemma": "chashav"
      },
      {
        "surface": "the one who presented it",
        "lemma": "qarav"
      },
      {
        "surface": "an abomination",
        "lemma": "piggul"
      },
      {
        "surface": "and the one",
        "lemma": "nephesh"
      },
      {
        "surface": "who eats",
        "lemma": "akhal"
      },
      {
        "surface": "shall bear",
        "lemma": "nasa"
      },
      {
        "surface": "his iniquity",
        "lemma": "avan"
      }
    ],
    "19": [
      {
        "surface": "Meat",
        "lemma": "basar"
      },
      {
        "surface": "touches",
        "lemma": "naga"
      },
      {
        "surface": "unclean",
        "lemma": "tame"
      },
      {
        "surface": "be eaten",
        "lemma": "akhal"
      },
      {
        "surface": "vvv",
        "lemma": "esh"
      },
      {
        "surface": "it is to be burned up",
        "lemma": "saraph"
      },
      {
        "surface": "As for",
        "lemma": "basar"
      },
      {
        "surface": "any other meat",
        "lemma": "basar"
      },
      {
        "surface": "who is ceremonially clean",
        "lemma": "tahor"
      },
      {
        "surface": "may eat it",
        "lemma": "akhal"
      }
    ],
    "20": [
      {
        "surface": "But if anyone",
        "lemma": "nephesh"
      },
      {
        "surface": "is unclean",
        "lemma": "tumah"
      },
      {
        "surface": "eats",
        "lemma": "akhal"
      },
      {
        "surface": "meat",
        "lemma": "basar"
      },
      {
        "surface": "vvv",
        "lemma": "zevach"
      },
      {
        "surface": "from the peace offering",
        "lemma": "shelem"
      },
      {
        "surface": "belongs to the LORD",
        "lemma": "yehovah"
      },
      {
        "surface": "person",
        "lemma": "nephesh"
      },
      {
        "surface": "must be cut off",
        "lemma": "karat"
      },
      {
        "surface": "from his people",
        "lemma": "am"
      }
    ],
    "21": [
      {
        "surface": "one",
        "lemma": "nephesh"
      },
      {
        "surface": "touches",
        "lemma": "naga"
      },
      {
        "surface": "unclean",
        "lemma": "tame"
      },
      {
        "surface": "human",
        "lemma": "adam"
      },
      {
        "surface": "uncleanness",
        "lemma": "tumah"
      },
      {
        "surface": "an unclean",
        "lemma": "tame"
      },
      {
        "surface": "animal",
        "lemma": "behemah"
      },
      {
        "surface": "unclean",
        "lemma": "tame"
      },
      {
        "surface": "detestable thing",
        "lemma": "sheqets"
      },
      {
        "surface": "and then eats",
        "lemma": "akhal"
      },
      {
        "surface": "any of the meat",
        "lemma": "basar"
      },
      {
        "surface": "vvv",
        "lemma": "zevach"
      },
      {
        "surface": "of the peace offering",
        "lemma": "shelem"
      },
      {
        "surface": "belongs to the LORD",
        "lemma": "yehovah"
      },
      {
        "surface": "person",
        "lemma": "nephesh"
      },
      {
        "surface": "must be cut off",
        "lemma": "karat"
      },
      {
        "surface": "from his people",
        "lemma": "am"
      }
    ],
    "22": [
      {
        "surface": "Then the LORD",
        "lemma": "yehovah"
      },
      {
        "surface": "said",
        "lemma": "davar"
      },
      {
        "surface": "Moses",
        "lemma": "mosheh"
      }
    ],
    "23": [
      {
        "surface": "Speak",
        "lemma": "davar"
      },
      {
        "surface": "the Israelites",
        "lemma": "ben"
      },
      {
        "surface": "to eat",
        "lemma": "akhal"
      },
      {
        "surface": "of the fat",
        "lemma": "chelev"
      },
      {
        "surface": "of an ox",
        "lemma": "shor"
      },
      {
        "surface": "a sheep",
        "lemma": "kesev"
      },
      {
        "surface": "or a goat",
        "lemma": "ez"
      }
    ],
    "24": [
      {
        "surface": "The fat",
        "lemma": "chelev"
      },
      {
        "surface": "of an animal found dead",
        "lemma": "nevelah"
      },
      {
        "surface": "or mauled by wild beasts",
        "lemma": "terephah"
      },
      {
        "surface": "purpose",
        "lemma": "melakhah"
      },
      {
        "surface": "eat",
        "lemma": "akhal"
      },
      {
        "surface": "it",
        "lemma": "akhal"
      }
    ],
    "25": [
      {
        "surface": "eats",
        "lemma": "akhal"
      },
      {
        "surface": "the fat",
        "lemma": "chelev"
      },
      {
        "surface": "of an animal",
        "lemma": "behemah"
      },
      {
        "surface": "a food offering",
        "lemma": "ishshah"
      },
      {
        "surface": "may be presented",
        "lemma": "qarav"
      },
      {
        "surface": "to the LORD",
        "lemma": "yehovah"
      },
      {
        "surface": "the one",
        "lemma": "nephesh"
      },
      {
        "surface": "who eats it",
        "lemma": "akhal"
      },
      {
        "surface": "must be cut off",
        "lemma": "karat"
      },
      {
        "surface": "from his people",
        "lemma": "am"
      }
    ],
    "26": [
      {
        "surface": "eat",
        "lemma": "akhal"
      },
      {
        "surface": "the blood",
        "lemma": "dam"
      },
      {
        "surface": "of any bird",
        "lemma": "oph"
      },
      {
        "surface": "or animal",
        "lemma": "behemah"
      },
      {
        "surface": "of your dwellings",
        "lemma": "moshav"
      }
    ],
    "27": [
      {
        "surface": "eats",
        "lemma": "akhal"
      },
      {
        "surface": "blood",
        "lemma": "dam"
      },
      {
        "surface": "person",
        "lemma": "nephesh"
      },
      {
        "surface": "must be cut off",
        "lemma": "karat"
      },
      {
        "surface": "from his people",
        "lemma": "am"
      }
    ],
    "28": [
      {
        "surface": "Then the LORD",
        "lemma": "yehovah"
      },
      {
        "surface": "said",
        "lemma": "davar"
      },
      {
        "surface": "Moses",
        "lemma": "mosheh"
      }
    ],
    "29": [
      {
        "surface": "Speak",
        "lemma": "davar"
      },
      {
        "surface": "the Israelites",
        "lemma": "ben"
      },
      {
        "surface": "Anyone who presents",
        "lemma": "qarav"
      },
      {
        "surface": "vvv",
        "lemma": "zevach"
      },
      {
        "surface": "a peace offering",
        "lemma": "shelem"
      },
      {
        "surface": "to the LORD",
        "lemma": "yehovah"
      },
      {
        "surface": "it",
        "lemma": "qorban"
      },
      {
        "surface": "as his sacrifice",
        "lemma": "zevach"
      },
      {
        "surface": "to the LORD",
        "lemma": "yehovah"
      }
    ],
    "30": [
      {
        "surface": "With his own hands",
        "lemma": "yad"
      },
      {
        "surface": "the food offerings",
        "lemma": "ishshah"
      },
      {
        "surface": "to the LORD",
        "lemma": "yehovah"
      },
      {
        "surface": "the fat",
        "lemma": "chelev"
      },
      {
        "surface": "the breast",
        "lemma": "chazeh"
      },
      {
        "surface": "and wave",
        "lemma": "nuph"
      },
      {
        "surface": "the breast",
        "lemma": "chazeh"
      },
      {
        "surface": "as a wave offering",
        "lemma": "tenuphah"
      },
      {
        "surface": "before",
        "lemma": "paneh"
      },
      {
        "surface": "the LORD",
        "lemma": "yehovah"
      }
    ],
    "31": [
      {
        "surface": "The priest",
        "lemma": "kohen"
      },
      {
        "surface": "is to burn",
        "lemma": "qatar"
      },
      {
        "surface": "the fat",
        "lemma": "chelev"
      },
      {
        "surface": "on the altar",
        "lemma": "mizbeach"
      },
      {
        "surface": "but the breast",
        "lemma": "chazeh"
      },
      {
        "surface": "Aaron",
        "lemma": "haaron"
      },
      {
        "surface": "and his sons",
        "lemma": "ben"
      }
    ],
    "32": [
      {
        "surface": "the right",
        "lemma": "yamin"
      },
      {
        "surface": "thigh",
        "lemma": "shoq"
      },
      {
        "surface": "to the priest",
        "lemma": "kohen"
      },
      {
        "surface": "as a contribution",
        "lemma": "terumah"
      },
      {
        "surface": "vvv",
        "lemma": "zevach"
      },
      {
        "surface": "from your peace offering",
        "lemma": "shelem"
      }
    ],
    "33": [
      {
        "surface": "The son",
        "lemma": "ben"
      },
      {
        "surface": "of Aaron",
        "lemma": "haaron"
      },
      {
        "surface": "who presents",
        "lemma": "qarav"
      },
      {
        "surface": "the blood",
        "lemma": "dam"
      },
      {
        "surface": "fat",
        "lemma": "chelev"
      },
      {
        "surface": "of the peace offering",
        "lemma": "shelem"
      },
      {
        "surface": "the right",
        "lemma": "yamin"
      },
      {
        "surface": "thigh",
        "lemma": "shoq"
      },
      {
        "surface": "as a portion",
        "lemma": "manah"
      }
    ],
    "34": [
      {
        "surface": "I have taken",
        "lemma": "laqach"
      },
      {
        "surface": "from the sons",
        "lemma": "ben"
      },
      {
        "surface": "of Israel",
        "lemma": "yisrael"
      },
      {
        "surface": "the breast",
        "lemma": "chazeh"
      },
      {
        "surface": "of the wave offering",
        "lemma": "tenuphah"
      },
      {
        "surface": "and the thigh",
        "lemma": "shoq"
      },
      {
        "surface": "of the contribution",
        "lemma": "terumah"
      },
      {
        "surface": "vvv",
        "lemma": "zevach"
      },
      {
        "surface": "of their peace offerings",
        "lemma": "shelem"
      },
      {
        "surface": "to Aaron",
        "lemma": "haaron"
      },
      {
        "surface": "the priest",
        "lemma": "kohen"
      },
      {
        "surface": "and his sons",
        "lemma": "ben"
      },
      {
        "surface": "as a permanent",
        "lemma": "olam"
      },
      {
        "surface": "portion",
        "lemma": "choq"
      },
      {
        "surface": "from the sons",
        "lemma": "ben"
      },
      {
        "surface": "of Israel",
        "lemma": "yisrael"
      }
    ],
    "35": [
      {
        "surface": "is the portion",
        "lemma": "mishchah"
      },
      {
        "surface": "of the food offerings",
        "lemma": "ishshah"
      },
      {
        "surface": "to the LORD",
        "lemma": "yehovah"
      },
      {
        "surface": "for Aaron",
        "lemma": "haaron"
      },
      {
        "surface": "and his sons",
        "lemma": "ben"
      },
      {
        "surface": "since the day",
        "lemma": "yom"
      },
      {
        "surface": "they were presented",
        "lemma": "qarav"
      },
      {
        "surface": "to serve the LORD",
        "lemma": "yehovah"
      },
      {
        "surface": "as priests",
        "lemma": "kahan"
      }
    ],
    "36": [
      {
        "surface": "On the day",
        "lemma": "yom"
      },
      {
        "surface": "they were anointed",
        "lemma": "mashach"
      },
      {
        "surface": "the LORD",
        "lemma": "yehovah"
      },
      {
        "surface": "commanded that",
        "lemma": "tsavah"
      },
      {
        "surface": "the sons",
        "lemma": "ben"
      },
      {
        "surface": "of Israel",
        "lemma": "yisrael"
      },
      {
        "surface": "It is a permanent",
        "lemma": "olam"
      },
      {
        "surface": "portion",
        "lemma": "chuqqah"
      },
      {
        "surface": "for the generations to come",
        "lemma": "dor"
      }
    ],
    "37": [
      {
        "surface": "is the law",
        "lemma": "torah"
      },
      {
        "surface": "of the burnt offering",
        "lemma": "olah"
      },
      {
        "surface": "the grain offering",
        "lemma": "minchah"
      },
      {
        "surface": "the sin offering",
        "lemma": "chattaah"
      },
      {
        "surface": "the guilt offering",
        "lemma": "asham"
      },
      {
        "surface": "the ordination offering",
        "lemma": "millu"
      },
      {
        "surface": "vvv",
        "lemma": "zevach"
      },
      {
        "surface": "and the peace offering",
        "lemma": "shelem"
      }
    ],
    "38": [
      {
        "surface": "the LORD",
        "lemma": "yehovah"
      },
      {
        "surface": "gave",
        "lemma": "tsavah"
      },
      {
        "surface": "Moses",
        "lemma": "mosheh"
      },
      {
        "surface": "on Mount",
        "lemma": "har"
      },
      {
        "surface": "Sinai",
        "lemma": "sinay"
      },
      {
        "surface": "on the day",
        "lemma": "yom"
      },
      {
        "surface": "He commanded",
        "lemma": "tsavah"
      },
      {
        "surface": "the Israelites",
        "lemma": "ben"
      },
      {
        "surface": "to present",
        "lemma": "qarav"
      },
      {
        "surface": "their offerings",
        "lemma": "qorban"
      },
      {
        "surface": "to the LORD",
        "lemma": "yehovah"
      },
      {
        "surface": "in the Wilderness",
        "lemma": "midbar"
      },
      {
        "surface": "of Sinai",
        "lemma": "sinay"
      }
    ]
  },
  "themeLemmas": [
    "akhal",
    "zevach",
    "qarav"
  ]
}